checkifvalid/__init__.py
checkifvalid/rfc1738.py
checkifvalid/rfc3986.py
checkifvalid/rfc5234.py
checkifvalid/rfc5322.py
checkifvalid/rfc5954.py
tests/__init__.py
tests/test_email.py
tests/test_hostname.py
tests/test_ip4.py
tests/test_ip6.py
tests/test_mac.py
tests/test_uri.py
tests/test_url.py
checkifvalid-0.1.1.dist-info/LICENSE
checkifvalid-0.1.1.dist-info/METADATA
checkifvalid-0.1.1.dist-info/WHEEL
checkifvalid-0.1.1.dist-info/top_level.txt
checkifvalid-0.1.1.dist-info/RECORD
