Metadata-Version: 2.1
Name: checkifvalid
Version: 0.1.1
Summary: Syntax validator for email, hostname, url, uri and ip address, compliant to RFC specifications 
Home-page: https://github.com/dmachard/python-checkifvalid
Author: Denis MACHARD
Author-email: d.machard@gmail.com
Keywords: ipv6 ipv4 syntax validator regex
Platform: any
Classifier: License :: OSI Approved :: MIT License
Classifier: Programming Language :: Python :: 3
Classifier: Operating System :: OS Independent
Classifier: Topic :: Software Development :: Libraries
License-File: LICENSE
